examples/example_project/configs/comm.py
examples/example_project/configs/swint_cos.py
examples/example_project/configs/swint_cstar25_3x256.py
examples/example_project/configs/swint_cstar_1x256.py
examples/example_project/module/__init__.py
examples/example_project/module/mm_changeos.py
examples/example_project/module/mm_changestar2_5.py
examples/example_project/module/mm_changestar_1xd.py
torchange/__init__.py
torchange/configs/changen2/s1c1_cstar_vitb_1x256.py
torchange/configs/changen2/s1c1_cstar_vitl_1x256.py
torchange/configs/changen2/s1c5_cstar_vitb_1x256.py
torchange/configs/changen2/s9c1_cstar_vitb_1x256.py
torchange/configs/changeos/cos_r101.py
torchange/configs/changeos/cos_r18.py
torchange/configs/changeos/cos_r34.py
torchange/configs/changeos/cos_r50.py
torchange/configs/changeos/cos_swint.py
torchange/data/__init__.py
torchange/data/bitemporal.py
torchange/data/bright.py
torchange/data/hf_builder.py
torchange/data/levircd.py
torchange/data/s2looking.py
torchange/data/second.py
torchange/data/xView2.py
torchange/metrics/__init__.py
torchange/metrics/bcd.py
torchange/metrics/bright.py
torchange/metrics/scd.py
torchange/metrics/second.py
torchange/metrics/xview2.py
torchange/models/__init__.py
torchange/models/changemask.py
torchange/models/changeos.py
torchange/models/changesparse.py
torchange/models/changestar2.py
torchange/models/changestar2_5.py
torchange/models/changestar_1xd.py
torchange/models/neds.py
torchange/models/changen2/__init__.py
torchange/models/changen2/_changestar_1x256.py
torchange/models/changen2/change_event_simulation.py
torchange/models/changen2/rsdit.py
torchange/models/segment_any_change/__init__.py
torchange/models/segment_any_change/anychange.py
torchange/models/segment_any_change/base.py
torchange/models/segment_any_change/simple_maskgen.py
torchange/models/segment_any_change/viz.py
torchange/models/segment_any_change/segment_anything/__init__.py
torchange/models/segment_any_change/segment_anything/automatic_mask_generator.py
torchange-0.0.4.dist-info/licenses/LICENSE
torchange-0.0.4.dist-info/METADATA
torchange-0.0.4.dist-info/WHEEL
torchange-0.0.4.dist-info/top_level.txt
torchange-0.0.4.dist-info/RECORD
