Metadata-Version: 2.4
Name: torchange
Version: 0.0.4
Summary: A Unified Change Representation Learning Benchmark Library
Author-email: Zhuo Zheng <zhuozheng@cs.stanford.edu>
License:                                  Apache License
Keywords: Remote Sensing,Earth Vision,Change Detection,Change Generation
Classifier: Development Status :: 4 - Beta
Classifier: Operating System :: OS Independent
Classifier: Programming Language :: Python :: 3.8
Classifier: Programming Language :: Python :: 3.9
Classifier: Programming Language :: Python :: 3.10
Classifier: Programming Language :: Python :: 3.11
Classifier: Topic :: Utilities
Classifier: Topic :: Scientific/Engineering :: Artificial Intelligence
Classifier: Topic :: Scientific/Engineering :: GIS
Requires-Python: >=3.8
License-File: LICENSE
Requires-Dist: numpy
Requires-Dist: albumentations>=0.4.2
Requires-Dist: tifffile
Requires-Dist: scikit-image
Requires-Dist: tqdm
Requires-Dist: einops
Requires-Dist: timm
Requires-Dist: datasets[vision]
Requires-Dist: ever-beta
Dynamic: license-file
